<?xml version="1.0" encoding="utf-8"?>
<Document>
  <Engineering version="V18" />
  <SW.Blocks.FC ID="0">
    <AttributeList>
      <AutoNumber>true</AutoNumber>
      <HeaderAuthor />
      <HeaderFamily />
      <HeaderName />
      <HeaderVersion>0.1</HeaderVersion>
      <Interface><Sections xmlns="http://www.siemens.com/automation/Openness/SW/Interface/v5">
  <Section Name="Input" />
  <Section Name="Output" />
  <Section Name="InOut" />
  <Section Name="Temp" />
  <Section Name="Constant" />
  <Section Name="Return">
    <Member Name="Ret_Val" Datatype="Void" Accessibility="Public" />
  </Section>
</Sections></Interface>
      <IsIECCheckEnabled>false</IsIECCheckEnabled>
      <MemoryLayout>Optimized</MemoryLayout>
      <Name>Deaering sequences</Name>
      <Namespace />
      <Number>4</Number>
      <ProgrammingLanguage>LAD</ProgrammingLanguage>
      <SetENOAutomatically>false</SetENOAutomatically>
      <UDABlockProperties />
      <UDAEnableTagReadback>false</UDAEnableTagReadback>
    </AttributeList>
    <ObjectList>
      <MultilingualText ID="1" CompositionName="Comment">
        <ObjectList>
          <MultilingualTextItem ID="2" CompositionName="Items">
            <AttributeList>
              <Culture>en-GB</Culture>
              <Text />
            </AttributeList>
          </MultilingualTextItem>
          <MultilingualTextItem ID="3" CompositionName="Items">
            <AttributeList>
              <Culture>sv-SE</Culture>
              <Text />
            </AttributeList>
          </MultilingualTextItem>
          <MultilingualTextItem ID="4" CompositionName="Items">
            <AttributeList>
              <Culture>de-DE</Culture>
              <Text />
            </AttributeList>
          </MultilingualTextItem>
        </ObjectList>
      </MultilingualText>
      <SW.Blocks.CompileUnit ID="5" CompositionName="CompileUnits">
        <AttributeList>
          <NetworkSource><FlgNet xmlns="http://www.siemens.com/automation/Openness/SW/NetworkSource/FlgNet/v4">
  <Parts>
    <Access Scope="GlobalVariable" UId="21">
      <Symbol>
        <Component Name="Function Dearing with valve" />
        <Component Name="Input A" />
        <Component Name="set time" />
      </Symbol>
    </Access>
    <Access Scope="GlobalVariable" UId="22">
      <Symbol>
        <Component Name="delaytimes" />
        <Component Name="Outlet ON to pump ON A" />
      </Symbol>
    </Access>
    <Access Scope="GlobalVariable" UId="23">
      <Symbol>
        <Component Name="delaytimes" />
        <Component Name="Pump off to Outlet Close" />
      </Symbol>
    </Access>
    <Access Scope="GlobalVariable" UId="24">
      <Symbol>
        <Component Name="Function Dearing with valve" />
        <Component Name="Control A" />
        <Component Name="start deaaring" />
      </Symbol>
    </Access>
    <Access Scope="GlobalVariable" UId="25">
      <Symbol>
        <Component Name="Function Dearing with valve" />
        <Component Name="Control A" />
        <Component Name="stop dearing" />
      </Symbol>
    </Access>
    <Access Scope="GlobalVariable" UId="26">
      <Symbol>
        <Component Name="Function Dearing with valve" />
        <Component Name="Control A" />
        <Component Name="dearing running" />
      </Symbol>
    </Access>
    <Access Scope="GlobalVariable" UId="27">
      <Symbol>
        <Component Name="Function Dearing with valve" />
        <Component Name="Control A" />
        <Component Name="dearing Completed" />
      </Symbol>
    </Access>
    <Access Scope="GlobalVariable" UId="28">
      <Symbol>
        <Component Name="Function Dearing with valve" />
        <Component Name="Output A" />
        <Component Name="ON pump" />
      </Symbol>
    </Access>
    <Access Scope="GlobalVariable" UId="29">
      <Symbol>
        <Component Name="Function Dearing with valve" />
        <Component Name="Output A" />
        <Component Name="On outlet valve" />
      </Symbol>
    </Access>
    <Access Scope="GlobalVariable" UId="30">
      <Symbol>
        <Component Name="Function Dearing with valve" />
        <Component Name="Output A" />
        <Component Name="running time" />
      </Symbol>
    </Access>
    <Call UId="31">
      <CallInfo Name="FB5-Dearing with valve" BlockType="FB">
        <Instance Scope="GlobalVariable" UId="32">
          <Component Name="FB5-Dearing with valveA_DB" />
        </Instance>
        <Parameter Name="Time" Section="Input" Type="DInt" />
        <Parameter Name="Pump ON delay" Section="Input" Type="DInt" />
        <Parameter Name="Pump OFF delay" Section="Input" Type="DInt" />
        <Parameter Name="dispensing Time PV" Section="Output" Type="Int" />
        <Parameter Name="Start Dearing" Section="InOut" Type="Bool" />
        <Parameter Name="Stop Dearing" Section="InOut" Type="Bool" />
        <Parameter Name="Dearing Running" Section="InOut" Type="Bool" />
        <Parameter Name="Dearing completed" Section="InOut" Type="Bool" />
        <Parameter Name="ON Gear Pump" Section="InOut" Type="Bool" />
        <Parameter Name="ON valve" Section="InOut" Type="Bool" />
      </CallInfo>
    </Call>
  </Parts>
  <Wires>
    <Wire UId="33">
      <Powerrail />
      <NameCon UId="31" Name="en" />
    </Wire>
    <Wire UId="34">
      <IdentCon UId="21" />
      <NameCon UId="31" Name="Time" />
    </Wire>
    <Wire UId="35">
      <IdentCon UId="22" />
      <NameCon UId="31" Name="Pump ON delay" />
    </Wire>
    <Wire UId="36">
      <IdentCon UId="23" />
      <NameCon UId="31" Name="Pump OFF delay" />
    </Wire>
    <Wire UId="37">
      <IdentCon UId="24" />
      <NameCon UId="31" Name="Start Dearing" />
    </Wire>
    <Wire UId="38">
      <IdentCon UId="25" />
      <NameCon UId="31" Name="Stop Dearing" />
    </Wire>
    <Wire UId="39">
      <IdentCon UId="26" />
      <NameCon UId="31" Name="Dearing Running" />
    </Wire>
    <Wire UId="40">
      <IdentCon UId="27" />
      <NameCon UId="31" Name="Dearing completed" />
    </Wire>
    <Wire UId="41">
      <IdentCon UId="28" />
      <NameCon UId="31" Name="ON Gear Pump" />
    </Wire>
    <Wire UId="42">
      <IdentCon UId="29" />
      <NameCon UId="31" Name="ON valve" />
    </Wire>
    <Wire UId="43">
      <NameCon UId="31" Name="dispensing Time PV" />
      <IdentCon UId="30" />
    </Wire>
  </Wires>
</FlgNet></NetworkSource>
          <ProgrammingLanguage>LAD</ProgrammingLanguage>
        </AttributeList>
        <ObjectList>
          <MultilingualText ID="6" CompositionName="Comment">
            <ObjectList>
              <MultilingualTextItem ID="7" CompositionName="Items">
                <AttributeList>
                  <Culture>en-GB</Culture>
                  <Text />
                </AttributeList>
              </MultilingualTextItem>
              <MultilingualTextItem ID="8" CompositionName="Items">
                <AttributeList>
                  <Culture>sv-SE</Culture>
                  <Text />
                </AttributeList>
              </MultilingualTextItem>
              <MultilingualTextItem ID="9" CompositionName="Items">
                <AttributeList>
                  <Culture>de-DE</Culture>
                  <Text />
                </AttributeList>
              </MultilingualTextItem>
            </ObjectList>
          </MultilingualText>
          <MultilingualText ID="A" CompositionName="Title">
            <ObjectList>
              <MultilingualTextItem ID="B" CompositionName="Items">
                <AttributeList>
                  <Culture>en-GB</Culture>
                  <Text>Dearing A with valve</Text>
                </AttributeList>
              </MultilingualTextItem>
              <MultilingualTextItem ID="C" CompositionName="Items">
                <AttributeList>
                  <Culture>sv-SE</Culture>
                  <Text />
                </AttributeList>
              </MultilingualTextItem>
              <MultilingualTextItem ID="D" CompositionName="Items">
                <AttributeList>
                  <Culture>de-DE</Culture>
                  <Text />
                </AttributeList>
              </MultilingualTextItem>
            </ObjectList>
          </MultilingualText>
        </ObjectList>
      </SW.Blocks.CompileUnit>
      <SW.Blocks.CompileUnit ID="E" CompositionName="CompileUnits">
        <AttributeList>
          <NetworkSource><FlgNet xmlns="http://www.siemens.com/automation/Openness/SW/NetworkSource/FlgNet/v4">
  <Parts>
    <Access Scope="GlobalVariable" UId="21">
      <Symbol>
        <Component Name="Function Dearing with valve" />
        <Component Name="Input B" />
        <Component Name="set time" />
      </Symbol>
    </Access>
    <Access Scope="GlobalVariable" UId="22">
      <Symbol>
        <Component Name="delaytimes" />
        <Component Name="Outlet On to pump ON B" />
      </Symbol>
    </Access>
    <Access Scope="GlobalVariable" UId="23">
      <Symbol>
        <Component Name="delaytimes" />
        <Component Name="Pump off to Outlet Close" />
      </Symbol>
    </Access>
    <Access Scope="GlobalVariable" UId="24">
      <Symbol>
        <Component Name="Function Dearing with valve" />
        <Component Name="Control B" />
        <Component Name="start deaaring" />
      </Symbol>
    </Access>
    <Access Scope="GlobalVariable" UId="25">
      <Symbol>
        <Component Name="Function Dearing with valve" />
        <Component Name="Control B" />
        <Component Name="stop dearing" />
      </Symbol>
    </Access>
    <Access Scope="GlobalVariable" UId="26">
      <Symbol>
        <Component Name="Function Dearing with valve" />
        <Component Name="Control B" />
        <Component Name="dearing running" />
      </Symbol>
    </Access>
    <Access Scope="GlobalVariable" UId="27">
      <Symbol>
        <Component Name="Function Dearing with valve" />
        <Component Name="Control B" />
        <Component Name="dearing Completed" />
      </Symbol>
    </Access>
    <Access Scope="GlobalVariable" UId="28">
      <Symbol>
        <Component Name="Function Dearing with valve" />
        <Component Name="Output B" />
        <Component Name="ON pump" />
      </Symbol>
    </Access>
    <Access Scope="GlobalVariable" UId="29">
      <Symbol>
        <Component Name="Function Dearing with valve" />
        <Component Name="Output B" />
        <Component Name="On outlet valve" />
      </Symbol>
    </Access>
    <Access Scope="GlobalVariable" UId="30">
      <Symbol>
        <Component Name="Function Dearing with valve" />
        <Component Name="Output B" />
        <Component Name="running time" />
      </Symbol>
    </Access>
    <Call UId="31">
      <CallInfo Name="FB5-Dearing with valve" BlockType="FB">
        <Instance Scope="GlobalVariable" UId="32">
          <Component Name="FB5-Dearing with valveB_DB" />
        </Instance>
        <Parameter Name="Time" Section="Input" Type="DInt" />
        <Parameter Name="Pump ON delay" Section="Input" Type="DInt" />
        <Parameter Name="Pump OFF delay" Section="Input" Type="DInt" />
        <Parameter Name="dispensing Time PV" Section="Output" Type="Int" />
        <Parameter Name="Start Dearing" Section="InOut" Type="Bool" />
        <Parameter Name="Stop Dearing" Section="InOut" Type="Bool" />
        <Parameter Name="Dearing Running" Section="InOut" Type="Bool" />
        <Parameter Name="Dearing completed" Section="InOut" Type="Bool" />
        <Parameter Name="ON Gear Pump" Section="InOut" Type="Bool" />
        <Parameter Name="ON valve" Section="InOut" Type="Bool" />
      </CallInfo>
    </Call>
  </Parts>
  <Wires>
    <Wire UId="33">
      <Powerrail />
      <NameCon UId="31" Name="en" />
    </Wire>
    <Wire UId="34">
      <IdentCon UId="21" />
      <NameCon UId="31" Name="Time" />
    </Wire>
    <Wire UId="35">
      <IdentCon UId="22" />
      <NameCon UId="31" Name="Pump ON delay" />
    </Wire>
    <Wire UId="36">
      <IdentCon UId="23" />
      <NameCon UId="31" Name="Pump OFF delay" />
    </Wire>
    <Wire UId="37">
      <IdentCon UId="24" />
      <NameCon UId="31" Name="Start Dearing" />
    </Wire>
    <Wire UId="38">
      <IdentCon UId="25" />
      <NameCon UId="31" Name="Stop Dearing" />
    </Wire>
    <Wire UId="39">
      <IdentCon UId="26" />
      <NameCon UId="31" Name="Dearing Running" />
    </Wire>
    <Wire UId="40">
      <IdentCon UId="27" />
      <NameCon UId="31" Name="Dearing completed" />
    </Wire>
    <Wire UId="41">
      <IdentCon UId="28" />
      <NameCon UId="31" Name="ON Gear Pump" />
    </Wire>
    <Wire UId="42">
      <IdentCon UId="29" />
      <NameCon UId="31" Name="ON valve" />
    </Wire>
    <Wire UId="43">
      <NameCon UId="31" Name="dispensing Time PV" />
      <IdentCon UId="30" />
    </Wire>
  </Wires>
</FlgNet></NetworkSource>
          <ProgrammingLanguage>LAD</ProgrammingLanguage>
        </AttributeList>
        <ObjectList>
          <MultilingualText ID="F" CompositionName="Comment">
            <ObjectList>
              <MultilingualTextItem ID="10" CompositionName="Items">
                <AttributeList>
                  <Culture>en-GB</Culture>
                  <Text />
                </AttributeList>
              </MultilingualTextItem>
              <MultilingualTextItem ID="11" CompositionName="Items">
                <AttributeList>
                  <Culture>sv-SE</Culture>
                  <Text />
                </AttributeList>
              </MultilingualTextItem>
              <MultilingualTextItem ID="12" CompositionName="Items">
                <AttributeList>
                  <Culture>de-DE</Culture>
                  <Text />
                </AttributeList>
              </MultilingualTextItem>
            </ObjectList>
          </MultilingualText>
          <MultilingualText ID="13" CompositionName="Title">
            <ObjectList>
              <MultilingualTextItem ID="14" CompositionName="Items">
                <AttributeList>
                  <Culture>en-GB</Culture>
                  <Text>Dearing B with valve</Text>
                </AttributeList>
              </MultilingualTextItem>
              <MultilingualTextItem ID="15" CompositionName="Items">
                <AttributeList>
                  <Culture>sv-SE</Culture>
                  <Text />
                </AttributeList>
              </MultilingualTextItem>
              <MultilingualTextItem ID="16" CompositionName="Items">
                <AttributeList>
                  <Culture>de-DE</Culture>
                  <Text />
                </AttributeList>
              </MultilingualTextItem>
            </ObjectList>
          </MultilingualText>
        </ObjectList>
      </SW.Blocks.CompileUnit>
      <SW.Blocks.CompileUnit ID="17" CompositionName="CompileUnits">
        <AttributeList>
          <NetworkSource />
          <ProgrammingLanguage>LAD</ProgrammingLanguage>
        </AttributeList>
        <ObjectList>
          <MultilingualText ID="18" CompositionName="Comment">
            <ObjectList>
              <MultilingualTextItem ID="19" CompositionName="Items">
                <AttributeList>
                  <Culture>en-GB</Culture>
                  <Text />
                </AttributeList>
              </MultilingualTextItem>
              <MultilingualTextItem ID="1A" CompositionName="Items">
                <AttributeList>
                  <Culture>sv-SE</Culture>
                  <Text />
                </AttributeList>
              </MultilingualTextItem>
              <MultilingualTextItem ID="1B" CompositionName="Items">
                <AttributeList>
                  <Culture>de-DE</Culture>
                  <Text />
                </AttributeList>
              </MultilingualTextItem>
            </ObjectList>
          </MultilingualText>
          <MultilingualText ID="1C" CompositionName="Title">
            <ObjectList>
              <MultilingualTextItem ID="1D" CompositionName="Items">
                <AttributeList>
                  <Culture>en-GB</Culture>
                  <Text>Dearing A without Valve</Text>
                </AttributeList>
              </MultilingualTextItem>
              <MultilingualTextItem ID="1E" CompositionName="Items">
                <AttributeList>
                  <Culture>sv-SE</Culture>
                  <Text />
                </AttributeList>
              </MultilingualTextItem>
              <MultilingualTextItem ID="1F" CompositionName="Items">
                <AttributeList>
                  <Culture>de-DE</Culture>
                  <Text />
                </AttributeList>
              </MultilingualTextItem>
            </ObjectList>
          </MultilingualText>
        </ObjectList>
      </SW.Blocks.CompileUnit>
      <SW.Blocks.CompileUnit ID="20" CompositionName="CompileUnits">
        <AttributeList>
          <NetworkSource />
          <ProgrammingLanguage>LAD</ProgrammingLanguage>
        </AttributeList>
        <ObjectList>
          <MultilingualText ID="21" CompositionName="Comment">
            <ObjectList>
              <MultilingualTextItem ID="22" CompositionName="Items">
                <AttributeList>
                  <Culture>en-GB</Culture>
                  <Text />
                </AttributeList>
              </MultilingualTextItem>
              <MultilingualTextItem ID="23" CompositionName="Items">
                <AttributeList>
                  <Culture>sv-SE</Culture>
                  <Text />
                </AttributeList>
              </MultilingualTextItem>
              <MultilingualTextItem ID="24" CompositionName="Items">
                <AttributeList>
                  <Culture>de-DE</Culture>
                  <Text />
                </AttributeList>
              </MultilingualTextItem>
            </ObjectList>
          </MultilingualText>
          <MultilingualText ID="25" CompositionName="Title">
            <ObjectList>
              <MultilingualTextItem ID="26" CompositionName="Items">
                <AttributeList>
                  <Culture>en-GB</Culture>
                  <Text>Dearing B without Valve</Text>
                </AttributeList>
              </MultilingualTextItem>
              <MultilingualTextItem ID="27" CompositionName="Items">
                <AttributeList>
                  <Culture>sv-SE</Culture>
                  <Text />
                </AttributeList>
              </MultilingualTextItem>
              <MultilingualTextItem ID="28" CompositionName="Items">
                <AttributeList>
                  <Culture>de-DE</Culture>
                  <Text />
                </AttributeList>
              </MultilingualTextItem>
            </ObjectList>
          </MultilingualText>
        </ObjectList>
      </SW.Blocks.CompileUnit>
      <MultilingualText ID="29" CompositionName="Title">
        <ObjectList>
          <MultilingualTextItem ID="2A" CompositionName="Items">
            <AttributeList>
              <Culture>en-GB</Culture>
              <Text />
            </AttributeList>
          </MultilingualTextItem>
          <MultilingualTextItem ID="2B" CompositionName="Items">
            <AttributeList>
              <Culture>sv-SE</Culture>
              <Text />
            </AttributeList>
          </MultilingualTextItem>
          <MultilingualTextItem ID="2C" CompositionName="Items">
            <AttributeList>
              <Culture>de-DE</Culture>
              <Text />
            </AttributeList>
          </MultilingualTextItem>
        </ObjectList>
      </MultilingualText>
    </ObjectList>
  </SW.Blocks.FC>
</Document>